MANIFEST.in
README.rst
setup.py
aliyun_python_sdk_ots.egg-info/PKG-INFO
aliyun_python_sdk_ots.egg-info/SOURCES.txt
aliyun_python_sdk_ots.egg-info/dependency_links.txt
aliyun_python_sdk_ots.egg-info/requires.txt
aliyun_python_sdk_ots.egg-info/top_level.txt
aliyunsdkots/__init__.py
aliyunsdkots/request/__init__.py
aliyunsdkots/request/v20160620/BindInstance2VpcRequest.py
aliyunsdkots/request/v20160620/DeleteInstanceRequest.py
aliyunsdkots/request/v20160620/DeleteTagsRequest.py
aliyunsdkots/request/v20160620/GetInstanceRequest.py
aliyunsdkots/request/v20160620/InsertInstanceRequest.py
aliyunsdkots/request/v20160620/InsertTagsRequest.py
aliyunsdkots/request/v20160620/ListClusterTypeRequest.py
aliyunsdkots/request/v20160620/ListInstanceRequest.py
aliyunsdkots/request/v20160620/ListTagsRequest.py
aliyunsdkots/request/v20160620/ListVpcInfoByInstanceRequest.py
aliyunsdkots/request/v20160620/ListVpcInfoByVpcRequest.py
aliyunsdkots/request/v20160620/UnbindInstance2VpcRequest.py
aliyunsdkots/request/v20160620/UpdateInstanceRequest.py
aliyunsdkots/request/v20160620/__init__.py